smtpdfix/__init__.py
smtpdfix/authenticator.py
smtpdfix/certs.py
smtpdfix/configuration.py
smtpdfix/controller.py
smtpdfix/event_handler.py
smtpdfix/fixture.py
smtpdfix/handlers.py
smtpdfix/py.typed
smtpdfix/smtp.py
smtpdfix-0.5.2.dist-info/LICENSE
smtpdfix-0.5.2.dist-info/METADATA
smtpdfix-0.5.2.dist-info/WHEEL
smtpdfix-0.5.2.dist-info/entry_points.txt
smtpdfix-0.5.2.dist-info/top_level.txt
smtpdfix-0.5.2.dist-info/RECORD
