Metadata-Version: 2.1
Name: smtpdfix
Version: 0.5.2
Summary: A SMTP server for use as a pytest fixture that implements encryption and authentication for testing.
Home-page: https://github.com/bebleo/smtpdfix
Author: James Warne
Author-email: bebleo@yahoo.com
License: MIT
Project-URL: Source, https://github.com/bebleo/smtpdfix
Project-URL: Documentation, https://github.com/bebleo/smtpdfix#readme
Project-URL: Issues, https://github.com/bebleo/smtpdfix/issues
Classifier: Framework :: Pytest
Classifier: License :: OSI Approved :: MIT License
Classifier: Operating System :: OS Independent
Classifier: Programming Language :: Python :: 3
Classifier: Programming Language :: Python :: 3 :: Only
Classifier: Programming Language :: Python :: 3.8
Classifier: Programming Language :: Python :: 3.9
Classifier: Programming Language :: Python :: 3.10
Classifier: Programming Language :: Python :: 3.11
Classifier: Programming Language :: Python :: Implementation :: CPython
Classifier: Programming Language :: Python :: Implementation :: PyPy
Requires-Python: >=3.8
License-File: LICENSE
Requires-Dist: aiosmtpd
Requires-Dist: cryptography
Requires-Dist: portpicker
Requires-Dist: pytest
Provides-Extra: dev
Requires-Dist: smtpdfix[testing] ; extra == 'dev'
Requires-Dist: tox ; extra == 'dev'
Provides-Extra: testing
Requires-Dist: flake8 ; extra == 'testing'
Requires-Dist: isort ; extra == 'testing'
Requires-Dist: mypy ; extra == 'testing'
Requires-Dist: pytest-asyncio ; extra == 'testing'
Requires-Dist: pytest-cov ; extra == 'testing'
Requires-Dist: pytest-timeout ; extra == 'testing'
